quantum_vqe/__init__.py
quantum_vqe/utils.py
quantum_vqe/vqe.py
tests/__init__.py
tests/test_vqe.py
quantum_vqe-0.1.2.1.dist-info/LICENSE.md
quantum_vqe-0.1.2.1.dist-info/METADATA
quantum_vqe-0.1.2.1.dist-info/WHEEL
quantum_vqe-0.1.2.1.dist-info/top_level.txt
quantum_vqe-0.1.2.1.dist-info/RECORD
