Metadata-Version: 2.1
Name: quantum-vqe
Version: 0.1.2.1
Summary: A quantum VQE package
Home-page: https://github.com/SweatyCrayfish/quantum_vqe
Author: Viktor Veselov
License-File: LICENSE.md
Requires-Dist: qiskit
Requires-Dist: numpy
Requires-Dist: scipy
